usine.py
usine-0.2.3.dist-info/LICENSE
usine-0.2.3.dist-info/METADATA
usine-0.2.3.dist-info/WHEEL
usine-0.2.3.dist-info/top_level.txt
usine-0.2.3.dist-info/RECORD
