Metadata-Version: 2.1
Name: usine
Version: 0.2.3
Summary: Minimalist remote tasks execution via SSH.
Home-page: https://github.com/pyrates/usine
License: MIT
Keywords: ssh deployment
Platform: UNKNOWN
Classifier: Development Status :: 4 - Beta
Classifier: Intended Audience :: Developers
Classifier: License :: OSI Approved :: MIT License
Classifier: Operating System :: OS Independent
Classifier: Programming Language :: Python
Classifier: Programming Language :: Python :: 3.6
Classifier: Programming Language :: Python :: 3.7
Classifier: Programming Language :: Python :: 3.8
Requires-Dist: paramiko (==2.7.1)
Requires-Dist: progressist (==0.1.0)
Requires-Dist: PyYAML (==5.2)
Provides-Extra: test
Requires-Dist: pytest (==5.3.2) ; extra == 'test'
